idp_solver/Assignments.py
idp_solver/Expression.py
idp_solver/IDP_Z3.py
idp_solver/Idp.tx
idp_solver/Idp_to_Z3.py
idp_solver/Parse.py
idp_solver/Problem.py
idp_solver/Propagate.py
idp_solver/Run.py
idp_solver/Simplify.py
idp_solver/Substitute.py
idp_solver/__init__.py
idp_solver/utils.py
idp_solver-0.7.3.dist-info/entry_points.txt
idp_solver-0.7.3.dist-info/LICENSE.md
idp_solver-0.7.3.dist-info/WHEEL
idp_solver-0.7.3.dist-info/METADATA
idp_solver-0.7.3.dist-info/RECORD
